main.py
argus_overview/__init__.py
argus_overview/core/__init__.py
argus_overview/core/character_manager.py
argus_overview/core/config_watcher.py
argus_overview/core/discovery.py
argus_overview/core/eve_settings_sync.py
argus_overview/core/hotkey_manager.py
argus_overview/core/layout_manager.py
argus_overview/core/position.py
argus_overview/core/window_capture_threaded.py
argus_overview/esi/__init__.py
argus_overview/esi/client.py
argus_overview/esi/route_service.py
argus_overview/esi/universe_cache.py
argus_overview/intel/__init__.py
argus_overview/intel/alerts.py
argus_overview/intel/log_watcher.py
argus_overview/intel/parser.py
argus_overview/ui/__init__.py
argus_overview/ui/about_dialog.py
argus_overview/ui/action_registry.py
argus_overview/ui/characters_teams_tab.py
argus_overview/ui/hotkey_edit.py
argus_overview/ui/hotkeys_tab.py
argus_overview/ui/intel_tab.py
argus_overview/ui/layouts_tab.py
argus_overview/ui/main_tab.py
argus_overview/ui/main_window_v21.py
argus_overview/ui/menu_builder.py
argus_overview/ui/settings_manager.py
argus_overview/ui/settings_sync_tab.py
argus_overview/ui/settings_tab.py
argus_overview/ui/themes.py
argus_overview/ui/tray.py
argus_overview/utils/__init__.py
argus_overview/utils/constants.py
argus_overview/utils/display_server.py
argus_overview/utils/screen.py
argus_overview/utils/window_utils.py
argus_overview-2.10.0.dist-info/licenses/LICENSE
argus_overview-2.10.0.dist-info/METADATA
argus_overview-2.10.0.dist-info/WHEEL
argus_overview-2.10.0.dist-info/entry_points.txt
argus_overview-2.10.0.dist-info/top_level.txt
argus_overview-2.10.0.dist-info/RECORD
