Metadata-Version: 2.4
Name: argus-overview
Version: 2.10.0
Summary: Professional multi-boxing tool for EVE Online on Linux
Author: AreteDriver
License: MIT
Project-URL: Homepage, https://github.com/AreteDriver/Argus_Overview
Project-URL: Repository, https://github.com/AreteDriver/Argus_Overview.git
Project-URL: Issues, https://github.com/AreteDriver/Argus_Overview/issues
Project-URL: Changelog, https://github.com/AreteDriver/Argus_Overview/blob/main/CHANGELOG.md
Keywords: eve-online,multiboxing,linux,gaming,preview,pyside6,argus,overview
Classifier: Development Status :: 4 - Beta
Classifier: Environment :: X11 Applications :: Qt
Classifier: Intended Audience :: End Users/Desktop
Classifier: License :: OSI Approved :: MIT License
Classifier: Operating System :: POSIX :: Linux
Classifier: Programming Language :: Python :: 3
Classifier: Programming Language :: Python :: 3.10
Classifier: Programming Language :: Python :: 3.11
Classifier: Programming Language :: Python :: 3.12
Classifier: Topic :: Games/Entertainment
Requires-Python: >=3.10
License-File: LICENSE
Requires-Dist: PySide6>=6.6.0
Requires-Dist: python-xlib>=0.33
Requires-Dist: Pillow>=10.0.0
Requires-Dist: pynput>=1.7.0
Requires-Dist: numpy>=1.24.0
Requires-Dist: watchdog>=4.0.0
Requires-Dist: httpx>=0.27.0
Provides-Extra: dev
Requires-Dist: ruff; extra == "dev"
Requires-Dist: isort; extra == "dev"
Requires-Dist: pytest; extra == "dev"
Requires-Dist: pytest-cov; extra == "dev"
Requires-Dist: bandit[toml]; extra == "dev"
Dynamic: license-file
